{"last_node_id":19,"last_link_id":21,"nodes":[{"id":12,"type":"PtDataLoader","pos":[2290.658447265625,2016.2130126953125],"size":[271.68658447265625,173.3039093017578],"flags":{},"order":5,"mode":0,"inputs":[{"name":"dataset","localized_name":"dataset","type":"PTVDATASET","link":10}],"outputs":[{"name":"PTDATALOADER","localized_name":"PTDATALOADER","type":"PTDATALOADER","links":[14],"slot_index":0}],"properties":{"Node name for S&R":"PtDataLoader"},"widgets_values":[128,false,"{\"num_workers\":1}"]},{"id":7,"type":"PtDataLoader","pos":[2293.7060546875,1735.56494140625],"size":[271.68658447265625,173.3039093017578],"flags":{},"order":4,"mode":0,"inputs":[{"name":"dataset","localized_name":"dataset","type":"PTVDATASET","link":11}],"outputs":[{"name":"PTDATALOADER","localized_name":"PTDATALOADER","type":"PTDATALOADER","links":[13],"slot_index":0}],"properties":{"Node name for S&R":"PtDataLoader"},"widgets_values":[128,true,"{\"num_workers\":1}"]},{"id":14,"type":"PtTrainRNNModel","pos":[3111.27294921875,1735.56494140625],"size":[315,326],"flags":{},"order":8,"mode":0,"inputs":[{"name":"model","localized_name":"model","type":"PTMODEL","link":12},{"name":"train_loader","localized_name":"train_loader","type":"PTDATALOADER","link":13},{"name":"optimizer","localized_name":"optimizer","type":"PTOPTIMIZER","link":17},{"name":"loss_function","localized_name":"loss_function","type":"PTLOSS","link":18},{"name":"scheduler","localized_name":"scheduler","type":"PTLRSCHEDULER","shape":7,"link":16},{"name":"val_loader","localized_name":"val_loader","type":"PTDATALOADER","shape":7,"link":14}],"outputs":[{"name":"Model","localized_name":"Model","type":"PTMODEL","links":[19],"slot_index":0},{"name":"train loss","localized_name":"train loss","type":"TENSOR","links":null},{"name":"val loss","localized_name":"val loss","type":"TENSOR","links":null}],"properties":{"Node name for S&R":"PtTrainRNNModel"},"widgets_values":[true,50,true,false,10,false,true,true]},{"id":16,"type":"PtnBCEWithLogitsLoss","pos":[2668.492919921875,1800.2408447265625],"size":[315,58],"flags":{},"order":0,"mode":0,"inputs":[],"outputs":[{"name":"PTLOSS","localized_name":"PTLOSS","type":"PTLOSS","links":[18],"slot_index":0}],"properties":{"Node name for S&R":"PtnBCEWithLogitsLoss"},"widgets_values":["mean"]},{"id":10,"type":"PtvHfGloveDataset","pos":[1927.5224609375,1735.56494140625],"size":[315,178],"flags":{},"order":1,"mode":0,"inputs":[],"outputs":[{"name":"PTVDATASET","localized_name":"PTVDATASET","type":"PTVDATASET","links":[11],"slot_index":0}],"properties":{"Node name for S&R":"PtvHfGloveDataset"},"widgets_values":["imdb","train",100,300,"text","label"]},{"id":11,"type":"PtvHfGloveDataset","pos":[1920.82177734375,2017.7349853515625],"size":[315,178],"flags":{},"order":2,"mode":0,"inputs":[],"outputs":[{"name":"PTVDATASET","localized_name":"PTVDATASET","type":"PTVDATASET","links":[10],"slot_index":0}],"properties":{"Node name for S&R":"PtvHfGloveDataset"},"widgets_values":["imdb","test",100,300,"text","label"]},{"id":9,"type":"PtoAdam","pos":[2668.492919921875,1191.617431640625],"size":[315,106],"flags":{},"order":6,"mode":0,"inputs":[{"name":"model","localized_name":"model","type":"PTMODEL","link":21}],"outputs":[{"name":"PTOPTIMIZER","localized_name":"PTOPTIMIZER","type":"PTOPTIMIZER","links":[15,17],"slot_index":0}],"properties":{"Node name for S&R":"PtoAdam"},"widgets_values":[0.001,0.9,0.999]},{"id":15,"type":"PtoLrSchedulerReduceOnPlateau","pos":[3111.27294921875,1377.6142578125],"size":[314.1559143066406,82],"flags":{},"order":7,"mode":0,"inputs":[{"name":"optimizer","localized_name":"optimizer","type":"PTOPTIMIZER","link":15}],"outputs":[{"name":"PTLRSCHEDULER","localized_name":"PTLRSCHEDULER","type":"PTLRSCHEDULER","links":[16],"slot_index":0}],"properties":{"Node name for S&R":"PtoLrSchedulerReduceOnPlateau"},"widgets_values":[3,0.5000000000000002]},{"id":19,"type":"PandasShowText","pos":[3504.62841796875,1897.03662109375],"size":[302.7994079589844,100],"flags":{},"order":10,"mode":0,"inputs":[{"name":"text","type":"STRING","widget":{"name":"text"},"link":20}],"outputs":[{"name":"STRING","localized_name":"STRING","type":"STRING","shape":6,"links":null}],"properties":{"Node name for S&R":"PandasShowText"},"widgets_values":["","/container/transfer/models/rnn_classification.pt"]},{"id":17,"type":"PtSaveModel","pos":[3495.453125,1735.56494140625],"size":[318.3275146484375,91.27499389648438],"flags":{},"order":9,"mode":0,"inputs":[{"name":"model","localized_name":"model","type":"PTMODEL","link":19}],"outputs":[{"name":"model full path","localized_name":"model full path","type":"STRING","links":[20],"slot_index":0}],"properties":{"Node name for S&R":"PtSaveModel"},"widgets_values":["/container/transfer/models/rnn_classification.pt"]},{"id":13,"type":"PtnRNNLinear","pos":[2668.492919921875,1374.7393798828125],"size":[315,274],"flags":{},"order":3,"mode":0,"inputs":[],"outputs":[{"name":"PTMODEL","localized_name":"PTMODEL","type":"PTMODEL","links":[12,21],"slot_index":0}],"properties":{"Node name for S&R":"PtnRNNLinear"},"widgets_values":[100,128,2,"tanh",true,true,0.1,true,1,true]}],"links":[[10,11,0,12,0,"PTVDATASET"],[11,10,0,7,0,"PTVDATASET"],[12,13,0,14,0,"PTMODEL"],[13,7,0,14,1,"PTDATALOADER"],[14,12,0,14,5,"PTDATALOADER"],[15,9,0,15,0,"PTOPTIMIZER"],[16,15,0,14,4,"PTLRSCHEDULER"],[17,9,0,14,2,"PTOPTIMIZER"],[18,16,0,14,3,"PTLOSS"],[19,14,0,17,0,"PTMODEL"],[20,17,0,19,0,"STRING"],[21,13,0,9,0,"PTMODEL"]],"groups":[],"config":{},"extra":{"ds":{"scale":0.7036873299402207,"offset":[-1643.4385821927863,-998.2899215112109]},"node_versions":{"pt-wrapper":"b4b5dc48f3843c4c802d035fac042d0d79bea5a1","data-analysis":"68dd090367adffa569c3b3993d56e422f4516d2d"},"ue_links":[]},"version":0.4}